sql/__init__.py
sql/_current.py
sql/_patch.py
sql/_testing.py
sql/column_guesser.py
sql/command.py
sql/display.py
sql/error_handler.py
sql/exceptions.py
sql/inspect.py
sql/magic.py
sql/magic_cmd.py
sql/magic_plot.py
sql/parse.py
sql/plot.py
sql/stats.py
sql/store.py
sql/traits.py
sql/util.py
sql/warnings.py
sql/cmd/__init__.py
sql/cmd/cmd_utils.py
sql/cmd/columns.py
sql/cmd/connect.py
sql/cmd/explore.py
sql/cmd/profile.py
sql/cmd/snippets.py
sql/cmd/tables.py
sql/cmd/test.py
sql/connection/__init__.py
sql/connection/connection.py
sql/connection/error_handling.py
sql/ggplot/__init__.py
sql/ggplot/aes.py
sql/ggplot/facet_wrap.py
sql/ggplot/ggplot.py
sql/ggplot/geom/__init__.py
sql/ggplot/geom/geom.py
sql/ggplot/geom/geom_boxplot.py
sql/ggplot/geom/geom_histogram.py
sql/run/__init__.py
sql/run/csv.py
sql/run/pgspecial.py
sql/run/resultset.py
sql/run/run.py
sql/run/sparkdataframe.py
sql/run/table.py
sql/widgets/__init__.py
sql/widgets/utils.py
sql/widgets/table_widget/__init__.py
sql/widgets/table_widget/table_widget.py
sql/widgets/table_widget/css/tableWidget.css
sql/widgets/table_widget/js/tableWidget.js
jupysql-0.11.0.dist-info/LICENSE
jupysql-0.11.0.dist-info/METADATA
jupysql-0.11.0.dist-info/WHEEL
jupysql-0.11.0.dist-info/top_level.txt
jupysql-0.11.0.dist-info/RECORD
