Metadata-Version: 2.2
Name: jupysql
Version: 0.11.0
Summary: Better SQL in Jupyter
Home-page: https://github.com/ploomber/jupysql
Author: Ploomber
Author-email: contact@ploomber.io
Project-URL: Source, https://github.com/ploomber/jupysql
Keywords: database ipython postgresql mysql duckdb
Classifier: Development Status :: 3 - Alpha
Classifier: Environment :: Console
Classifier: License :: OSI Approved :: Apache Software License
Classifier: Topic :: Database
Classifier: Topic :: Database :: Front-Ends
Classifier: Programming Language :: Python :: 3
License-File: LICENSE
Requires-Dist: prettytable>=3.12.0
Requires-Dist: ipython<=8.12.0; python_version <= "3.8"
Requires-Dist: sqlalchemy
Requires-Dist: sqlparse
Requires-Dist: ipython-genutils>=0.1.0
Requires-Dist: jinja2
Requires-Dist: sqlglot>=11.3.7
Requires-Dist: importlib-metadata; python_version < "3.8"
Requires-Dist: jupysql-plugin>=0.4.2
Requires-Dist: ploomber-core>=0.2.7
Provides-Extra: dev
Requires-Dist: flake8; extra == "dev"
Requires-Dist: pytest; extra == "dev"
Requires-Dist: pandas<2.2.0; extra == "dev"
Requires-Dist: polars==0.17.2; extra == "dev"
Requires-Dist: pyarrow; extra == "dev"
Requires-Dist: invoke; extra == "dev"
Requires-Dist: pkgmt; extra == "dev"
Requires-Dist: twine; extra == "dev"
Requires-Dist: duckdb<1.1.0; extra == "dev"
Requires-Dist: duckdb-engine; extra == "dev"
Requires-Dist: pyodbc; extra == "dev"
Requires-Dist: matplotlib==3.7.2; extra == "dev"
Requires-Dist: black; extra == "dev"
Requires-Dist: ipywidgets; extra == "dev"
Requires-Dist: js2py; extra == "dev"
Requires-Dist: psutil; extra == "dev"
Requires-Dist: jupyter-server; extra == "dev"
Provides-Extra: integration
Requires-Dist: flake8; extra == "integration"
Requires-Dist: pytest; extra == "integration"
Requires-Dist: pandas<2.2.0; extra == "integration"
Requires-Dist: polars==0.17.2; extra == "integration"
Requires-Dist: pyarrow; extra == "integration"
Requires-Dist: invoke; extra == "integration"
Requires-Dist: pkgmt; extra == "integration"
Requires-Dist: twine; extra == "integration"
Requires-Dist: duckdb<1.1.0; extra == "integration"
Requires-Dist: duckdb-engine; extra == "integration"
Requires-Dist: pyodbc; extra == "integration"
Requires-Dist: matplotlib==3.7.2; extra == "integration"
Requires-Dist: black; extra == "integration"
Requires-Dist: ipywidgets; extra == "integration"
Requires-Dist: js2py; extra == "integration"
Requires-Dist: psutil; extra == "integration"
Requires-Dist: jupyter-server; extra == "integration"
Requires-Dist: dockerctx; extra == "integration"
Requires-Dist: pyarrow; extra == "integration"
Requires-Dist: psycopg2-binary; extra == "integration"
Requires-Dist: pymysql; extra == "integration"
Requires-Dist: pgspecial==2.0.1; extra == "integration"
Requires-Dist: pyodbc; extra == "integration"
Requires-Dist: snowflake-sqlalchemy; extra == "integration"
Requires-Dist: oracledb; extra == "integration"
Requires-Dist: sqlalchemy-pytds; extra == "integration"
Requires-Dist: python-tds; extra == "integration"
Requires-Dist: redshift-connector; extra == "integration"
Requires-Dist: sqlalchemy-redshift; extra == "integration"
Requires-Dist: clickhouse-sqlalchemy; extra == "integration"
Requires-Dist: pyspark; extra == "integration"
Requires-Dist: grpcio-status; extra == "integration"
Dynamic: author
Dynamic: author-email
Dynamic: classifier
Dynamic: description
Dynamic: description-content-type
Dynamic: home-page
Dynamic: keywords
Dynamic: project-url
Dynamic: provides-extra
Dynamic: requires-dist
Dynamic: summary
